alibabacloud_quanmiaolightapp20240801/__init__.py
alibabacloud_quanmiaolightapp20240801/client.py
alibabacloud_quanmiaolightapp20240801/models/__init__.py
alibabacloud_quanmiaolightapp20240801/models/_cancel_async_task_request.py
alibabacloud_quanmiaolightapp20240801/models/_cancel_async_task_response.py
alibabacloud_quanmiaolightapp20240801/models/_cancel_async_task_response_body.py
alibabacloud_quanmiaolightapp20240801/models/_export_analysis_tag_detail_by_task_id_request.py
alibabacloud_quanmiaolightapp20240801/models/_export_analysis_tag_detail_by_task_id_response.py
alibabacloud_quanmiaolightapp20240801/models/_export_analysis_tag_detail_by_task_id_response_body.py
alibabacloud_quanmiaolightapp20240801/models/_export_analysis_tag_detail_by_task_id_shrink_request.py
alibabacloud_quanmiaolightapp20240801/models/_generate_broadcast_news_request.py
alibabacloud_quanmiaolightapp20240801/models/_generate_broadcast_news_response.py
alibabacloud_quanmiaolightapp20240801/models/_generate_broadcast_news_response_body.py
alibabacloud_quanmiaolightapp20240801/models/_generate_output_format_request.py
alibabacloud_quanmiaolightapp20240801/models/_generate_output_format_response.py
alibabacloud_quanmiaolightapp20240801/models/_generate_output_format_response_body.py
alibabacloud_quanmiaolightapp20240801/models/_generate_output_format_shrink_request.py
alibabacloud_quanmiaolightapp20240801/models/_get_enterprise_voc_analysis_task_request.py
alibabacloud_quanmiaolightapp20240801/models/_get_enterprise_voc_analysis_task_response.py
alibabacloud_quanmiaolightapp20240801/models/_get_enterprise_voc_analysis_task_response_body.py
alibabacloud_quanmiaolightapp20240801/models/_get_essay_correction_task_request.py
alibabacloud_quanmiaolightapp20240801/models/_get_essay_correction_task_response.py
alibabacloud_quanmiaolightapp20240801/models/_get_essay_correction_task_response_body.py
alibabacloud_quanmiaolightapp20240801/models/_get_file_content_request.py
alibabacloud_quanmiaolightapp20240801-2.13.6.dist-info/LICENSE
alibabacloud_quanmiaolightapp20240801-2.13.6.dist-info/METADATA
alibabacloud_quanmiaolightapp20240801-2.13.6.dist-info/WHEEL
alibabacloud_quanmiaolightapp20240801-2.13.6.dist-info/top_level.txt
alibabacloud_quanmiaolightapp20240801-2.13.6.dist-info/RECORD
